eurotronic_cometblue_ha-1.3.1.dist-info/METADATA
eurotronic_cometblue_ha-1.3.1.dist-info/WHEEL
eurotronic_cometblue_ha-1.3.1.dist-info/entry_points.txt
eurotronic_cometblue_ha-1.3.1.dist-info/licenses/LICENSE
eurotronic_cometblue_ha/__init__.py
eurotronic_cometblue_ha/const.py
eurotronic_cometblue_ha-1.3.1.dist-info/RECORD
