Metadata-Version: 2.4
Name: eurotronic-cometblue-ha
Version: 1.3.1
Summary: Python client for Eurotronic GmbH BLE Comet (and rebranded) Radiator TRVs.
Author-Email: Johannes Rottler <johannes@rottler.me>, Richard Kroegel <rikroe@users.noreply.github.com>
License-Expression: MIT
Classifier: Development Status :: 5 - Production/Stable
Classifier: Operating System :: MacOS :: MacOS X
Classifier: Operating System :: Microsoft :: Windows :: Windows 10
Classifier: Operating System :: POSIX :: Linux
Classifier: Programming Language :: Python :: 3.14
Classifier: Programming Language :: Python :: 3.13
Classifier: Programming Language :: Python :: 3.12
Classifier: Programming Language :: Python :: 3.11
Classifier: Programming Language :: Python :: 3.10
Project-URL: Source, https://github.com/rikroe/eurotronic-cometblue
Requires-Python: <4.0,>=3.10
Requires-Dist: bleak
Requires-Dist: bleak-retry-connector
